thomas/__init__.py
thomas/__main__.py
thomas/filesystem.py
thomas/httpserver.py
thomas/humanize.py
thomas/piece.py
thomas/plugin.py
thomas/txiobuffer.py
thomas/inputs/__init__.py
thomas/inputs/file.py
thomas/inputs/http.py
thomas/outputs/__init__.py
thomas/outputs/http.py
thomas/outputs/proxy.py
thomas/processors/__init__.py
thomas/processors/rar.py
thomas/processors/virtualfile.py
thomas/streamers/__init__.py
thomas/streamers/direct.py
thomas/streamers/rar.py
thomas/tests/__init__.py
thomas/tests/test_filesystem.py
thomas/tests/test_processors_virtualfile.py
thomas-2.2.3.dist-info/LICENSE
thomas-2.2.3.dist-info/METADATA
thomas-2.2.3.dist-info/WHEEL
thomas-2.2.3.dist-info/entry_points.txt
thomas-2.2.3.dist-info/top_level.txt
thomas-2.2.3.dist-info/RECORD
