Metadata-Version: 2.1
Name: thomas
Version: 2.2.3
Summary: Thomas allows segmented downloads and is an alternative to Axel
Home-page: https://github.com/JohnDoee/thomas
Author: Anders Jensen
Author-email: johndoee+thomas@tidalstream.org
Maintainer: Anders Jensen
License: MIT
Platform: UNKNOWN
Classifier: Development Status :: 4 - Beta
Classifier: Environment :: Console
Classifier: Intended Audience :: End Users/Desktop
Classifier: License :: OSI Approved :: MIT License
Classifier: Operating System :: POSIX :: BSD
Classifier: Operating System :: POSIX :: Linux
Classifier: Operating System :: POSIX :: Other
Classifier: Operating System :: Microsoft :: Windows
Classifier: Programming Language :: Python :: 2.7
Classifier: Programming Language :: Python :: 3.4
Classifier: Programming Language :: Python :: 3.5
Classifier: Programming Language :: Python :: 3.6
Classifier: Topic :: Internet :: WWW/HTTP
Requires-Dist: pytz
Requires-Dist: six
Requires-Dist: twisted
Requires-Dist: progressbar2
Requires-Dist: rfc6266
Requires-Dist: requests
Requires-Dist: rarfile
